<?xml version="1.0"?>
<Workbook xmlns="urn:schemas-microsoft-com:office:spreadsheet"
 xmlns:o="urn:schemas-microsoft-com:office:office"
 xmlns:x="urn:schemas-microsoft-com:office:excel"
 xmlns:ss="urn:schemas-microsoft-com:office:spreadsheet"
 xmlns:html="http://www.w3.org/TR/REC-html40">
 <DocumentProperties xmlns="urn:schemas-microsoft-com:office:office">
  <Author>konrad schlatte</Author>
  <LastAuthor>konrad schlatte</LastAuthor>
  <Created>2016-11-07T15:11:41Z</Created>
  <Version>14.0</Version>
 </DocumentProperties>
 <OfficeDocumentSettings xmlns="urn:schemas-microsoft-com:office:office">
  <AllowPNG/>
 </OfficeDocumentSettings>
 <ExcelWorkbook xmlns="urn:schemas-microsoft-com:office:excel">
  <WindowHeight>7640</WindowHeight>
  <WindowWidth>25600</WindowWidth>
  <WindowTopX>0</WindowTopX>
  <WindowTopY>-460</WindowTopY>
  <ProtectStructure>False</ProtectStructure>
  <ProtectWindows>False</ProtectWindows>
 </ExcelWorkbook>
 <Styles>
  <Style ss:ID="Default" ss:Name="Normal">
   <Alignment ss:Vertical="Bottom"/>
   <Borders/>
   <Font ss:FontName="Calibri" x:Family="Swiss" ss:Size="12" ss:Color="#000000"/>
   <Interior/>
   <NumberFormat/>
   <Protection/>
  </Style>
 </Styles>
 <Worksheet ss:Name="Sheet1">
  <Table ss:ExpandedColumnCount="2" ss:ExpandedRowCount="4" x:FullColumns="1"
   x:FullRows="1" ss:DefaultColumnWidth="65" ss:DefaultRowHeight="15">
   <Row ss:AutoFitHeight="0"/>
   <Row ss:Index="3" ss:AutoFitHeight="0">
    <Cell ss:Index="2"><Data ss:Type="String">Retirement</Data></Cell>
   </Row>
   <Row ss:AutoFitHeight="0">
    <Cell ss:Index="2"><Data ss:Type="String">index1.html</Data></Cell>
   </Row>
  </Table>
  <WorksheetOptions xmlns="urn:schemas-microsoft-com:office:excel">
   <Unsynced/>
   <PageLayoutZoom>0</PageLayoutZoom>
   <Selected/>
   <Panes>
    <Pane>
     <Number>3</Number>
     <ActiveRow>4</ActiveRow>
     <ActiveCol>1</ActiveCol>
    </Pane>
   </Panes>
   <ProtectObjects>False</ProtectObjects>
   <ProtectScenarios>False</ProtectScenarios>
  </WorksheetOptions>
 </Worksheet>
</Workbook>
